trcactivator/AppleColorEmoji.ttf
trcactivator/__init__.py
trcactivator/utils.py
trcactivator-0.0.3.dist-info/LICENSE
trcactivator-0.0.3.dist-info/METADATA
trcactivator-0.0.3.dist-info/WHEEL
trcactivator-0.0.3.dist-info/top_level.txt
trcactivator-0.0.3.dist-info/RECORD
