Metadata-Version: 2.1
Name: trcactivator
Version: 0.0.3
Summary: This package is designed to automate the activation of multi-checks from the @tonRocketBot bot from multiple Telegram accounts. The package uses the Telethon library to interact with the Telegram API.
Author-email: Conradk10 <orion25rus@gmail.com>
Project-URL: Homepage, https://github.com/Conradk10/trcactivator
Project-URL: Bug Tracker, https://github.com/Conradk10/trcactivator/issues
Classifier: Programming Language :: Python :: 3
Classifier: License :: OSI Approved :: MIT License
Classifier: Operating System :: OS Independent
Requires-Python: >=3.8
License-File: LICENSE
Requires-Dist: hikka-tl (==1.24.10)
Requires-Dist: loguru (==0.6.0)
Requires-Dist: numpy (==1.23.4)
Requires-Dist: opencv-python (==4.6.0.66)
Requires-Dist: Pillow (==9.3.0)
